appligen/__init__.py
appligen/admin.py
appligen/apps.py
appligen/cli.py
appligen/generator.py
appligen/models.py
appligen/run.py
appligen/tests.py
appligen/views.py
appligen/migrations/__init__.py
envgen/__init__.py
envgen/admin.py
envgen/apps.py
envgen/cli.py
envgen/models.py
envgen/tests.py
envgen/views.py
envgen/migrations/__init__.py
envgen_jaysimy-0.0.4.dist-info/METADATA
envgen_jaysimy-0.0.4.dist-info/WHEEL
envgen_jaysimy-0.0.4.dist-info/entry_points.txt
envgen_jaysimy-0.0.4.dist-info/top_level.txt
envgen_jaysimy-0.0.4.dist-info/RECORD
